[
  {
    "timestamp": "2025-07-16 23:55:48",
    "WETH": 0.00011131,
    "USDC": 0.25504049,
    "pool": {
      "krs_usdc": 975.3798794595659,
      "usdc": 764.82083,
      "krs_weth": 1593.1616019980136,
      "weth": 0.002060830787274543,
      "value_usd": 1013.76,
      "value_eth": 0.300965,
      "value_pln": 3707.88
    },
    "ETHPLN": 12319.97,
    "ETHUSD": 3368.36
  },
  {
    "timestamp": "2025-07-17 01:52:21",
    "WETH": 0.00011131,
    "USDC": 0.25504049,
    "pool": {
      "krs_usdc": 975.3798794595659,
      "usdc": 764.82083,
      "krs_weth": 1593.1616019980136,
      "weth": 0.002060830787274543,
      "value_usd": 1013.76,
      "value_eth": 0.303458,
      "value_pln": 3708.17
    },
    "ETHPLN": 12219.72,
    "ETHUSD": 3340.69
  },
  {
    "timestamp": "2025-07-17 03:27:33",
    "WETH": 0.00011131,
    "USDC": 0.25504049,
    "pool": {
      "krs_usdc": 975.3798794595659,
      "usdc": 764.82083,
      "krs_weth": 1593.1616019980136,
      "weth": 0.002060830787274543,
      "value_usd": 1013.76,
      "value_eth": 0.303797,
      "value_pln": 3709.78
    },
    "ETHPLN": 12211.36,
    "ETHUSD": 3336.96
  },
  {
    "timestamp": "2025-07-17 04:21:23",
    "WETH": 0.00011131,
    "USDC": 0.25504049,
    "pool": {
      "krs_usdc": 975.3798794595659,
      "usdc": 764.82083,
      "krs_weth": 1593.1616019980136,
      "weth": 0.002060830787274543,
      "value_usd": 1013.76,
      "value_eth": 0.303951,
      "value_pln": 3711.95
    },
    "ETHPLN": 12212.31,
    "ETHUSD": 3335.27
  },
  {
    "timestamp": "2025-07-17 04:57:39",
    "WETH": 0.00011131,
    "USDC": 0.25504049,
    "pool": {
      "krs_usdc": 975.3798794595659,
      "usdc": 764.82083,
      "krs_weth": 1593.1616019980136,
      "weth": 0.002060830787274543,
      "value_usd": 1013.76,
      "value_eth": 0.302793,
      "value_pln": 3709.65
    },
    "ETHPLN": 12251.46,
    "ETHUSD": 3348.03
  },
  {
    "timestamp": "2025-07-17 05:30:54",
    "WETH": 0.00011131,
    "USDC": 0.25504049,
    "pool": {
      "krs_usdc": 975.3798794595659,
      "usdc": 764.82083,
      "krs_weth": 1593.1616019980136,
      "weth": 0.002060830787274543,
      "value_usd": 1013.76,
      "value_eth": 0.302573,
      "value_pln": 3709.21
    },
    "ETHPLN": 12258.87,
    "ETHUSD": 3350.46
  },
  {
    "timestamp": "2025-07-17 05:52:53",
    "WETH": 0.00011131,
    "USDC": 0.25504049,
    "pool": {
      "krs_usdc": 975.3798794595659,
      "usdc": 764.82083,
      "krs_weth": 1593.1616019980136,
      "weth": 0.002060830787274543,
      "value_usd": 1013.76,
      "value_eth": 0.300638,
      "value_pln": 3709.57
    },
    "ETHPLN": 12339.01,
    "ETHUSD": 3372.03
  },
  {
    "timestamp": "2025-07-17 06:31:22",
    "WETH": 0.00011131,
    "USDC": 0.25504049,
    "pool": {
      "krs_usdc": 975.3798794595659,
      "usdc": 764.82083,
      "krs_weth": 1593.1616019980136,
      "weth": 0.002060830787274543,
      "value_usd": 1013.76,
      "value_eth": 0.295702,
      "value_pln": 3723.64
    },
    "ETHPLN": 12592.55,
    "ETHUSD": 3428.32
  },
  {
    "timestamp": "2025-07-17 06:58:38",
    "WETH": 0.00011131,
    "USDC": 0.25504049,
    "pool": {
      "krs_usdc": 975.3798794595659,
      "usdc": 764.82083,
      "krs_weth": 1593.1616019980136,
      "weth": 0.002060830787274543,
      "value_usd": 1013.76,
      "value_eth": 0.295429,
      "value_pln": 3722.89
    },
    "ETHPLN": 12601.64,
    "ETHUSD": 3431.48
  },
  {
    "timestamp": "2025-07-17 07:29:14",
    "WETH": 0.00011131,
    "USDC": 0.25504049,
    "pool": {
      "krs_usdc": 975.3798794595659,
      "usdc": 764.82083,
      "krs_weth": 1593.1616019980136,
      "weth": 0.002060830787274543,
      "value_usd": 1013.76,
      "value_eth": 0.296189,
      "value_pln": 3722.44
    },
    "ETHPLN": 12567.78,
    "ETHUSD": 3422.68
  },
  {
    "timestamp": "2025-07-17 07:45:13",
    "WETH": 0.00011131,
    "USDC": 0.25504049,
    "pool": {
      "krs_usdc": 975.3798794595659,
      "usdc": 764.82083,
      "krs_weth": 1593.1616019980136,
      "weth": 0.002060830787274543,
      "value_usd": 1013.76,
      "value_eth": 0.293985,
      "value_pln": 3718.11
    },
    "ETHPLN": 12647.3,
    "ETHUSD": 3448.34
  },
  {
    "timestamp": "2025-07-17 07:55:55",
    "WETH": 0.00011131,
    "USDC": 0.25504049,
    "pool": {
      "krs_usdc": 975.3798794595659,
      "usdc": 764.82083,
      "krs_weth": 1593.1616019980136,
      "weth": 0.002060830787274543,
      "value_usd": 1013.76,
      "value_eth": 0.293561,
      "value_pln": 3720.31
    },
    "ETHPLN": 12673.05,
    "ETHUSD": 3453.32
  },
  {
    "timestamp": "2025-07-17 08:30:20",
    "WETH": 0.00011131,
    "USDC": 0.25504049,
    "pool": {
      "krs_usdc": 975.3798794595659,
      "usdc": 764.82083,
      "krs_weth": 1593.1616019980136,
      "weth": 0.002060830787274543,
      "value_usd": 1013.76,
      "value_eth": 0.294721,
      "value_pln": 3716.47
    },
    "ETHPLN": 12610.13,
    "ETHUSD": 3439.73
  },
  {
    "timestamp": "2025-07-17 08:54:52",
    "WETH": 0.00011131,
    "USDC": 0.25504049,
    "pool": {
      "krs_usdc": 975.3798794595659,
      "usdc": 764.82083,
      "krs_weth": 1593.1616019980136,
      "weth": 0.002060830787274543,
      "value_usd": 1013.76,
      "value_eth": 0.295274,
      "value_pln": 3717.3
    },
    "ETHPLN": 12589.32,
    "ETHUSD": 3433.28
  },
  {
    "timestamp": "2025-07-17 09:25:17",
    "WETH": 0.00011131,
    "USDC": 0.25504049,
    "pool": {
      "krs_usdc": 975.3798794595659,
      "usdc": 764.82083,
      "krs_weth": 1593.1616019980136,
      "weth": 0.002060830787274543,
      "value_usd": 1013.76,
      "value_eth": 0.293336,
      "value_pln": 3720.53
    },
    "ETHPLN": 12683.51,
    "ETHUSD": 3455.97
  },
  {
    "timestamp": "2025-07-17 09:46:48",
    "WETH": 0.00011131,
    "USDC": 0.25504049,
    "pool": {
      "krs_usdc": 975.3798794595659,
      "usdc": 764.82083,
      "krs_weth": 1593.1616019980136,
      "weth": 0.002060830787274543,
      "value_usd": 1013.76,
      "value_eth": 0.292087,
      "value_pln": 3718.68
    },
    "ETHPLN": 12731.38,
    "ETHUSD": 3470.74
  },
  {
    "timestamp": "2025-07-17 09:57:20",
    "WETH": 0.00011131,
    "USDC": 0.25504049,
    "pool": {
      "krs_usdc": 975.3798794595659,
      "usdc": 764.82083,
      "krs_weth": 1593.1616019980136,
      "weth": 0.002060830787274543,
      "value_usd": 1013.76,
      "value_eth": 0.291812,
      "value_pln": 3721.33
    },
    "ETHPLN": 12752.5,
    "ETHUSD": 3474.02
  },
  {
    "timestamp": "2025-07-17 10:29:26",
    "WETH": 0.00011131,
    "USDC": 0.25504049,
    "pool": {
      "krs_usdc": 975.3798794595659,
      "usdc": 764.82083,
      "krs_weth": 1593.1616019980136,
      "weth": 0.002060830787274543,
      "value_usd": 1013.76,
      "value_eth": 0.292028,
      "value_pln": 3721.38
    },
    "ETHPLN": 12743.25,
    "ETHUSD": 3471.45
  },
  {
    "timestamp": "2025-07-17 10:51:11",
    "WETH": 0.00011131,
    "USDC": 0.25504049,
    "pool": {
      "krs_usdc": 975.3798794595659,
      "usdc": 764.82083,
      "krs_weth": 1593.1616019980136,
      "weth": 0.002060830787274543,
      "value_usd": 1013.76,
      "value_eth": 0.292953,
      "value_pln": 3721.18
    },
    "ETHPLN": 12702.3,
    "ETHUSD": 3460.48
  },
  {
    "timestamp": "2025-07-17 11:18:28",
    "WETH": 0.00011131,
    "USDC": 0.25504049,
    "pool": {
      "krs_usdc": 975.3798794595659,
      "usdc": 764.82083,
      "krs_weth": 1593.1616019980136,
      "weth": 0.002060830787274543,
      "value_usd": 1013.76,
      "value_eth": 0.2934,
      "value_pln": 3723.04
    },
    "ETHPLN": 12689.3,
    "ETHUSD": 3455.21
  },
  {
    "timestamp": "2025-07-17 11:35:39",
    "WETH": 0.00011131,
    "USDC": 0.25504049,
    "pool": {
      "krs_usdc": 975.3798794595659,
      "usdc": 764.82083,
      "krs_weth": 1593.1616019980136,
      "weth": 0.002060830787274543,
      "value_usd": 1013.76,
      "value_eth": 0.294581,
      "value_pln": 3725.85
    },
    "ETHPLN": 12647.96,
    "ETHUSD": 3441.36
  },
  {
    "timestamp": "2025-07-17 11:48:17",
    "WETH": 0.00011131,
    "USDC": 0.25504049,
    "pool": {
      "krs_usdc": 975.3798794595659,
      "usdc": 764.82083,
      "krs_weth": 1593.1616019980136,
      "weth": 0.002060830787274543,
      "value_usd": 1013.76,
      "value_eth": 0.294864,
      "value_pln": 3725.68
    },
    "ETHPLN": 12635.27,
    "ETHUSD": 3438.06
  },
  {
    "timestamp": "2025-07-17 11:58:48",
    "WETH": 0.00011131,
    "USDC": 0.25504049,
    "pool": {
      "krs_usdc": 975.3798794595659,
      "usdc": 764.82083,
      "krs_weth": 1593.1616019980136,
      "weth": 0.002060830787274543,
      "value_usd": 1013.76,
      "value_eth": 0.294974,
      "value_pln": 3727.57
    },
    "ETHPLN": 12636.96,
    "ETHUSD": 3436.78
  },
  {
    "timestamp": "2025-07-17 12:58:57",
    "WETH": 0.00011131,
    "USDC": 0.25504049,
    "pool": {
      "krs_usdc": 975.3798794595659,
      "usdc": 764.82083,
      "krs_weth": 1593.1616019980136,
      "weth": 0.002060830787274543,
      "value_usd": 1013.76,
      "value_eth": 0.295375,
      "value_pln": 3722.83
    },
    "ETHPLN": 12603.75,
    "ETHUSD": 3432.11
  },
  {
    "timestamp": "2025-07-17 13:42:22",
    "WETH": 0.00011131,
    "USDC": 0.25504049,
    "pool": {
      "krs_usdc": 975.3798794595659,
      "usdc": 764.82083,
      "krs_weth": 1593.1616019980136,
      "weth": 0.002060830787274543,
      "value_usd": 1013.76,
      "value_eth": 0.297051,
      "value_pln": 3724.69
    },
    "ETHPLN": 12538.91,
    "ETHUSD": 3412.75
  },
  {
    "timestamp": "2025-07-17 13:59:25",
    "WETH": 0.00011131,
    "USDC": 0.25504049,
    "pool": {
      "krs_usdc": 975.3798794595659,
      "usdc": 764.82083,
      "krs_weth": 1593.1616019980136,
      "weth": 0.002060830787274543,
      "value_usd": 1013.76,
      "value_eth": 0.297802,
      "value_pln": 3725.64
    },
    "ETHPLN": 12510.46,
    "ETHUSD": 3404.14
  },
  {
    "timestamp": "2025-07-17 14:28:44",
    "WETH": 0.00011131,
    "USDC": 0.25504049,
    "pool": {
      "krs_usdc": 975.3798794595659,
      "usdc": 764.82083,
      "krs_weth": 1593.1616019980136,
      "weth": 0.002060830787274543,
      "value_usd": 1013.76,
      "value_eth": 0.297005,
      "value_pln": 3721.52
    },
    "ETHPLN": 12530.19,
    "ETHUSD": 3413.28
  },
  {
    "timestamp": "2025-07-17 14:49:17",
    "WETH": 0.00011131,
    "USDC": 0.25504049,
    "pool": {
      "krs_usdc": 975.3798794595659,
      "usdc": 764.82083,
      "krs_weth": 1593.1616019980136,
      "weth": 0.002060830787274543,
      "value_usd": 1013.76,
      "value_eth": 0.296128,
      "value_pln": 3721.17
    },
    "ETHPLN": 12566.09,
    "ETHUSD": 3423.38
  },
  {
    "timestamp": "2025-07-17 14:59:30",
    "WETH": 0.00011131,
    "USDC": 0.25504049,
    "pool": {
      "krs_usdc": 975.3798794595659,
      "usdc": 764.82083,
      "krs_weth": 1593.1616019980136,
      "weth": 0.002060830787274543,
      "value_usd": 1013.76,
      "value_eth": 0.29559,
      "value_pln": 3723.1
    },
    "ETHPLN": 12595.48,
    "ETHUSD": 3429.61
  },
  {
    "timestamp": "2025-07-17 15:32:13",
    "WETH": 0.00011131,
    "USDC": 0.25504049,
    "pool": {
      "krs_usdc": 975.3798794595659,
      "usdc": 764.82083,
      "krs_weth": 1593.1616019980136,
      "weth": 0.002060830787274543,
      "value_usd": 1013.76,
      "value_eth": 0.297055,
      "value_pln": 3727.37
    },
    "ETHPLN": 12547.76,
    "ETHUSD": 3412.7
  },
  {
    "timestamp": "2025-07-17 15:51:48",
    "WETH": 0.00011131,
    "USDC": 0.25504049,
    "pool": {
      "krs_usdc": 975.3798794595659,
      "usdc": 764.82083,
      "krs_weth": 1593.1616019980136,
      "weth": 0.002060830787274543,
      "value_usd": 1013.76,
      "value_eth": 0.296627,
      "value_pln": 3722.53
    },
    "ETHPLN": 12549.51,
    "ETHUSD": 3417.62
  },
  {
    "timestamp": "2025-07-17 16:27:07",
    "WETH": 0.00011131,
    "USDC": 0.25504049,
    "pool": {
      "krs_usdc": 975.3798794595659,
      "usdc": 764.82083,
      "krs_weth": 1593.1616019980136,
      "weth": 0.002060830787274543,
      "value_usd": 1013.76,
      "value_eth": 0.298144,
      "value_pln": 3723.06
    },
    "ETHPLN": 12487.43,
    "ETHUSD": 3400.23
  },
  {
    "timestamp": "2025-07-17 16:52:23",
    "WETH": 0.00011131,
    "USDC": 0.25504049,
    "pool": {
      "krs_usdc": 975.3798794595659,
      "usdc": 764.82083,
      "krs_weth": 1593.1616019980136,
      "weth": 0.002060830787274543,
      "value_usd": 1013.76,
      "value_eth": 0.298255,
      "value_pln": 3727.82
    },
    "ETHPLN": 12498.77,
    "ETHUSD": 3398.97
  },
  {
    "timestamp": "2025-07-17 17:19:22",
    "WETH": 0.00011131,
    "USDC": 0.25504049,
    "pool": {
      "krs_usdc": 975.3798794595659,
      "usdc": 764.82083,
      "krs_weth": 1593.1616019980136,
      "weth": 0.002060830787274543,
      "value_usd": 1013.76,
      "value_eth": 0.297755,
      "value_pln": 3724.85
    },
    "ETHPLN": 12509.8,
    "ETHUSD": 3404.68
  },
  {
    "timestamp": "2025-07-17 17:40:55",
    "WETH": 0.00011131,
    "USDC": 0.25504049,
    "pool": {
      "krs_usdc": 975.3798794595659,
      "usdc": 764.82083,
      "krs_weth": 1593.1616019980136,
      "weth": 0.002060830787274543,
      "value_usd": 1013.76,
      "value_eth": 0.297853,
      "value_pln": 3726.0
    },
    "ETHPLN": 12509.55,
    "ETHUSD": 3403.56
  },
  {
    "timestamp": "2025-07-17 17:55:51",
    "WETH": 0.00011131,
    "USDC": 0.25504049,
    "pool": {
      "krs_usdc": 975.3798794595659,
      "usdc": 764.82083,
      "krs_weth": 1593.1616019980136,
      "weth": 0.002060830787274543,
      "value_usd": 1013.76,
      "value_eth": 0.296885,
      "value_pln": 3726.66
    },
    "ETHPLN": 12552.53,
    "ETHUSD": 3414.65
  },
  {
    "timestamp": "2025-07-17 18:33:15",
    "WETH": 0.00011131,
    "USDC": 0.25504049,
    "pool": {
      "krs_usdc": 975.3798794595659,
      "usdc": 764.82083,
      "krs_weth": 1593.1616019980136,
      "weth": 0.002060830787274543,
      "value_usd": 1013.76,
      "value_eth": 0.295261,
      "value_pln": 3727.29
    },
    "ETHPLN": 12623.73,
    "ETHUSD": 3433.44
  },
  {
    "timestamp": "2025-07-17 18:57:45",
    "WETH": 0.00011131,
    "USDC": 0.25504049,
    "pool": {
      "krs_usdc": 975.3798794595659,
      "usdc": 764.82083,
      "krs_weth": 1593.1616019980136,
      "weth": 0.002060830787274543,
      "value_usd": 1013.76,
      "value_eth": 0.295669,
      "value_pln": 3727.3
    },
    "ETHPLN": 12606.34,
    "ETHUSD": 3428.7
  },
  {
    "timestamp": "2025-07-17 19:22:45",
    "WETH": 0.00011131,
    "USDC": 0.25504049,
    "pool": {
      "krs_usdc": 975.3798794595659,
      "usdc": 764.82083,
      "krs_weth": 1593.1616019980136,
      "weth": 0.002060830787274543,
      "value_usd": 1013.76,
      "value_eth": 0.294578,
      "value_pln": 3725.81
    },
    "ETHPLN": 12647.97,
    "ETHUSD": 3441.4
  },
  {
    "timestamp": "2025-07-17 19:39:45",
    "WETH": 0.00011131,
    "USDC": 0.25504049,
    "pool": {
      "krs_usdc": 975.3798794595659,
      "usdc": 764.82083,
      "krs_weth": 1593.1616019980136,
      "weth": 0.002060830787274543,
      "value_usd": 1013.76,
      "value_eth": 0.293957,
      "value_pln": 3721.45
    },
    "ETHPLN": 12659.85,
    "ETHUSD": 3448.67
  },
  {
    "timestamp": "2025-07-17 19:50:18",
    "WETH": 0.00011131,
    "USDC": 0.25504049,
    "pool": {
      "krs_usdc": 975.3798794595659,
      "usdc": 764.82083,
      "krs_weth": 1593.1616019980136,
      "weth": 0.002060830787274543,
      "value_usd": 1013.76,
      "value_eth": 0.294898,
      "value_pln": 3719.34
    },
    "ETHPLN": 12612.28,
    "ETHUSD": 3437.66
  },
  {
    "timestamp": "2025-07-17 20:09:41",
    "WETH": 0.00011131,
    "USDC": 0.25504049,
    "pool": {
      "krs_usdc": 975.3798794595659,
      "usdc": 764.82083,
      "krs_weth": 1593.1616019980136,
      "weth": 0.002060830787274543,
      "value_usd": 1013.76,
      "value_eth": 0.297387,
      "value_pln": 3721.25
    },
    "ETHPLN": 12513.14,
    "ETHUSD": 3408.89
  },
  {
    "timestamp": "2025-07-17 20:35:17",
    "WETH": 0.00011131,
    "USDC": 0.25504049,
    "pool": {
      "krs_usdc": 975.3798794595659,
      "usdc": 764.82083,
      "krs_weth": 1593.1616019980136,
      "weth": 0.002060830787274543,
      "value_usd": 1013.76,
      "value_eth": 0.298196,
      "value_pln": 3722.22
    },
    "ETHPLN": 12482.46,
    "ETHUSD": 3399.64
  },
  {
    "timestamp": "2025-07-17 20:51:48",
    "WETH": 0.00011131,
    "USDC": 0.25504049,
    "pool": {
      "krs_usdc": 975.3798794595659,
      "usdc": 764.82083,
      "krs_weth": 1593.1616019980136,
      "weth": 0.002060830787274543,
      "value_usd": 1013.76,
      "value_eth": 0.296944,
      "value_pln": 3719.87
    },
    "ETHPLN": 12527.19,
    "ETHUSD": 3413.98
  },
  {
    "timestamp": "2025-07-17 21:19:30",
    "WETH": 0.00011131,
    "USDC": 0.25504049,
    "pool": {
      "krs_usdc": 975.3798794595659,
      "usdc": 764.82083,
      "krs_weth": 1593.1616019980136,
      "weth": 0.002060830787274543,
      "value_usd": 1013.76,
      "value_eth": 0.291099,
      "value_pln": 3723.84
    },
    "ETHPLN": 12792.33,
    "ETHUSD": 3482.52
  },
  {
    "timestamp": "2025-07-17 21:37:41",
    "WETH": 0.00011131,
    "USDC": 0.25504049,
    "pool": {
      "krs_usdc": 975.3798794595659,
      "usdc": 764.82083,
      "krs_weth": 1593.1616019980136,
      "weth": 0.002060830787274543,
      "value_usd": 1013.76,
      "value_eth": 0.291242,
      "value_pln": 3716.26
    },
    "ETHPLN": 12760.03,
    "ETHUSD": 3480.81
  },
  {
    "timestamp": "2025-07-17 21:49:43",
    "WETH": 0.00011131,
    "USDC": 0.25504049,
    "pool": {
      "krs_usdc": 975.3798794595659,
      "usdc": 764.82083,
      "krs_weth": 1593.1616019980136,
      "weth": 0.002060830787274543,
      "value_usd": 1013.76,
      "value_eth": 0.292314,
      "value_pln": 3720.52
    },
    "ETHPLN": 12727.82,
    "ETHUSD": 3468.05
  },
  {
    "timestamp": "2025-07-17 22:00:06",
    "WETH": 0.00011131,
    "USDC": 0.25504049,
    "pool": {
      "krs_usdc": 975.3798794595659,
      "usdc": 764.82083,
      "krs_weth": 1593.1616019980136,
      "weth": 0.002060830787274543,
      "value_usd": 1013.76,
      "value_eth": 0.29223,
      "value_pln": 3721.11
    },
    "ETHPLN": 12733.52,
    "ETHUSD": 3469.05
  },
  {
    "timestamp": "2025-07-17 22:29:32",
    "WETH": 0.00011131,
    "USDC": 0.25504049,
    "pool": {
      "krs_usdc": 975.3798794595659,
      "usdc": 764.82083,
      "krs_weth": 1593.1616019980136,
      "weth": 0.002060830787274543,
      "value_usd": 1013.76,
      "value_eth": 0.291554,
      "value_pln": 3719.7
    },
    "ETHPLN": 12758.2,
    "ETHUSD": 3477.09
  },
  {
    "timestamp": "2025-07-17 22:48:26",
    "WETH": 0.00011131,
    "USDC": 0.25504049,
    "pool": {
      "krs_usdc": 975.3798794595659,
      "usdc": 764.82083,
      "krs_weth": 1593.1616019980136,
      "weth": 0.002060830787274543,
      "value_usd": 1013.76,
      "value_eth": 0.291018,
      "value_pln": 3716.28
    },
    "ETHPLN": 12769.96,
    "ETHUSD": 3483.5
  },
  {
    "timestamp": "2025-07-17 22:58:31",
    "WETH": 0.00011131,
    "USDC": 0.25504049,
    "pool": {
      "krs_usdc": 975.3798794595659,
      "usdc": 764.82083,
      "krs_weth": 1593.1616019980136,
      "weth": 0.002060830787274543,
      "value_usd": 1013.76,
      "value_eth": 0.291994,
      "value_pln": 3714.7
    },
    "ETHPLN": 12721.83,
    "ETHUSD": 3471.85
  },
  {
    "timestamp": "2025-07-17 23:27:59",
    "WETH": 0.00011131,
    "USDC": 0.25504049,
    "pool": {
      "krs_usdc": 975.3798794595659,
      "usdc": 764.82083,
      "krs_weth": 1593.1616019980136,
      "weth": 0.002060830787274543,
      "value_usd": 1013.76,
      "value_eth": 0.288288,
      "value_pln": 3714.55
    },
    "ETHPLN": 12884.84,
    "ETHUSD": 3516.48
  },
  {
    "timestamp": "2025-07-17 23:44:22",
    "WETH": 0.00011131,
    "USDC": 0.25504049,
    "pool": {
      "krs_usdc": 975.3798794595659,
      "usdc": 764.82083,
      "krs_weth": 1593.1616019980136,
      "weth": 0.002060830787274543,
      "value_usd": 1013.76,
      "value_eth": 0.290797,
      "value_pln": 3713.66
    },
    "ETHPLN": 12770.63,
    "ETHUSD": 3486.14
  },
  {
    "timestamp": "2025-07-17 23:55:42",
    "WETH": 0.00011131,
    "USDC": 0.25504049,
    "pool": {
      "krs_usdc": 975.3798794595659,
      "usdc": 764.82083,
      "krs_weth": 1593.1616019980136,
      "weth": 0.002060830787274543,
      "value_usd": 1013.76,
      "value_eth": 0.291095,
      "value_pln": 3714.93
    },
    "ETHPLN": 12761.9,
    "ETHUSD": 3482.57
  },
  {
    "timestamp": "2025-07-18 01:54:04",
    "WETH": 0.00011131,
    "USDC": 0.25504049,
    "pool": {
      "krs_usdc": 975.3798794595659,
      "usdc": 764.82083,
      "krs_weth": 1593.1616019980136,
      "weth": 0.002060830787274543,
      "value_usd": 1013.76,
      "value_eth": 0.281183,
      "value_pln": 3710.59
    },
    "ETHPLN": 13196.38,
    "ETHUSD": 3605.34
  },
  {
    "timestamp": "2025-07-18 03:37:23",
    "WETH": 0.00011131,
    "USDC": 0.25504049,
    "pool": {
      "krs_usdc": 975.3798794595659,
      "usdc": 764.82083,
      "krs_weth": 1593.1616019980136,
      "weth": 0.002060830787274543,
      "value_usd": 1013.76,
      "value_eth": 0.281807,
      "value_pln": 3713.64
    },
    "ETHPLN": 13177.97,
    "ETHUSD": 3597.36
  },
  {
    "timestamp": "2025-07-18 04:24:38",
    "WETH": 0.00011131,
    "USDC": 0.25504049,
    "pool": {
      "krs_usdc": 975.3798794595659,
      "usdc": 764.82083,
      "krs_weth": 1593.1616019980136,
      "weth": 0.002060830787274543,
      "value_usd": 1013.76,
      "value_eth": 0.282586,
      "value_pln": 3715.0
    },
    "ETHPLN": 13146.46,
    "ETHUSD": 3587.44
  },
  {
    "timestamp": "2025-07-18 04:59:06",
    "WETH": 0.00011131,
    "USDC": 0.25504049,
    "pool": {
      "krs_usdc": 975.3798794595659,
      "usdc": 764.82083,
      "krs_weth": 1593.1616019980136,
      "weth": 0.002060830787274543,
      "value_usd": 1013.76,
      "value_eth": 0.280452,
      "value_pln": 3715.21
    },
    "ETHPLN": 13247.23,
    "ETHUSD": 3614.74
  },
  {
    "timestamp": "2025-07-18 05:33:54",
    "WETH": 0.00011131,
    "USDC": 0.25504049,
    "pool": {
      "krs_usdc": 975.3798794595659,
      "usdc": 764.82083,
      "krs_weth": 1593.1616019980136,
      "weth": 0.002060830787274543,
      "value_usd": 1013.76,
      "value_eth": 0.278282,
      "value_pln": 3717.07
    },
    "ETHPLN": 13357.2,
    "ETHUSD": 3642.92
  },
  {
    "timestamp": "2025-07-18 05:53:58",
    "WETH": 0.00011131,
    "USDC": 0.25504049,
    "pool": {
      "krs_usdc": 975.3798794595659,
      "usdc": 764.82083,
      "krs_weth": 1593.1616019980136,
      "weth": 0.002060830787274543,
      "value_usd": 1013.76,
      "value_eth": 0.277694,
      "value_pln": 3714.62
    },
    "ETHPLN": 13376.63,
    "ETHUSD": 3650.63
  },
  {
    "timestamp": "2025-07-18 06:31:27",
    "WETH": 0.00011131,
    "USDC": 0.25504049,
    "pool": {
      "krs_usdc": 975.3798794595659,
      "usdc": 764.82083,
      "krs_weth": 1593.1616019980136,
      "weth": 0.002060830787274543,
      "value_usd": 1013.76,
      "value_eth": 0.277978,
      "value_pln": 3716.07
    },
    "ETHPLN": 13368.21,
    "ETHUSD": 3646.9
  },
  {
    "timestamp": "2025-07-18 06:59:44",
    "WETH": 0.00011131,
    "USDC": 0.25504049,
    "pool": {
      "krs_usdc": 975.3798794595659,
      "usdc": 764.82083,
      "krs_weth": 1593.1616019980136,
      "weth": 0.002060830787274543,
      "value_usd": 1013.76,
      "value_eth": 0.27704,
      "value_pln": 3711.88
    },
    "ETHPLN": 13398.36,
    "ETHUSD": 3659.25
  },
  {
    "timestamp": "2025-07-18 07:30:16",
    "WETH": 0.00011131,
    "USDC": 0.25504049,
    "pool": {
      "krs_usdc": 975.3798794595659,
      "usdc": 764.82083,
      "krs_weth": 1593.1616019980136,
      "weth": 0.002060830787274543,
      "value_usd": 1013.76,
      "value_eth": 0.27808,
      "value_pln": 3710.52
    },
    "ETHPLN": 13343.35,
    "ETHUSD": 3645.57
  },
  {
    "timestamp": "2025-07-18 07:47:40",
    "WETH": 0.00011131,
    "USDC": 0.25504049,
    "pool": {
      "krs_usdc": 975.3798794595659,
      "usdc": 764.82083,
      "krs_weth": 1593.1616019980136,
      "weth": 0.002060830787274543,
      "value_usd": 1013.76,
      "value_eth": 0.278983,
      "value_pln": 3709.49
    },
    "ETHPLN": 13296.49,
    "ETHUSD": 3633.77
  },
  {
    "timestamp": "2025-07-18 07:58:14",
    "WETH": 0.00011131,
    "USDC": 0.25504049,
    "pool": {
      "krs_usdc": 975.3798794595659,
      "usdc": 764.82083,
      "krs_weth": 1593.1616019980136,
      "weth": 0.002060830787274543,
      "value_usd": 1013.76,
      "value_eth": 0.279651,
      "value_pln": 3709.09
    },
    "ETHPLN": 13263.28,
    "ETHUSD": 3625.09
  },
  {
    "timestamp": "2025-07-18 08:37:07",
    "WETH": 0.00011131,
    "USDC": 0.25504049,
    "pool": {
      "krs_usdc": 975.3798794595659,
      "usdc": 764.82083,
      "krs_weth": 1593.1616019980136,
      "weth": 0.002060830787274543,
      "value_usd": 1013.76,
      "value_eth": 0.280056,
      "value_pln": 3701.7
    },
    "ETHPLN": 13217.68,
    "ETHUSD": 3619.84
  },
  {
    "timestamp": "2025-07-18 08:58:07",
    "WETH": 0.00011131,
    "USDC": 0.25504049,
    "pool": {
      "krs_usdc": 975.3798794595659,
      "usdc": 764.82083,
      "krs_weth": 1593.1616019980136,
      "weth": 0.002060830787274543,
      "value_usd": 1013.76,
      "value_eth": 0.281211,
      "value_pln": 3702.66
    },
    "ETHPLN": 13166.86,
    "ETHUSD": 3604.98
  },
  {
    "timestamp": "2025-07-18 09:31:58",
    "WETH": 0.00011131,
    "USDC": 0.25504049,
    "pool": {
      "krs_usdc": 975.3798794595659,
      "usdc": 764.82083,
      "krs_weth": 1593.1616019980136,
      "weth": 0.002060830787274543,
      "value_usd": 1013.76,
      "value_eth": 0.281258,
      "value_pln": 3700.09
    },
    "ETHPLN": 13155.51,
    "ETHUSD": 3604.38
  },
  {
    "timestamp": "2025-07-18 09:52:24",
    "WETH": 0.00011131,
    "USDC": 0.25504049,
    "pool": {
      "krs_usdc": 975.3798794595659,
      "usdc": 764.82083,
      "krs_weth": 1593.1616019980136,
      "weth": 0.002060830787274543,
      "value_usd": 1013.76,
      "value_eth": 0.280655,
      "value_pln": 3706.81
    },
    "ETHPLN": 13207.7,
    "ETHUSD": 3612.12
  },
  {
    "timestamp": "2025-07-18 10:22:54",
    "WETH": 0.00011131,
    "USDC": 0.25504049,
    "pool": {
      "krs_usdc": 975.3798794595659,
      "usdc": 764.82083,
      "krs_weth": 1593.1616019980136,
      "weth": 0.002060830787274543,
      "value_usd": 1013.76,
      "value_eth": 0.280576,
      "value_pln": 3699.98
    },
    "ETHPLN": 13187.11,
    "ETHUSD": 3613.14
  },
  {
    "timestamp": "2025-07-18 10:49:26",
    "WETH": 0.00011131,
    "USDC": 0.25504049,
    "pool": {
      "krs_usdc": 975.3798794595659,
      "usdc": 764.82083,
      "krs_weth": 1593.1616019980136,
      "weth": 0.002060830787274543,
      "value_usd": 1013.76,
      "value_eth": 0.280764,
      "value_pln": 3698.25
    },
    "ETHPLN": 13172.09,
    "ETHUSD": 3610.72
  },
  {
    "timestamp": "2025-07-18 10:59:35",
    "WETH": 0.00011131,
    "USDC": 0.25504049,
    "pool": {
      "krs_usdc": 975.3798794595659,
      "usdc": 764.82083,
      "krs_weth": 1593.1616019980136,
      "weth": 0.002060830787274543,
      "value_usd": 1013.76,
      "value_eth": 0.280365,
      "value_pln": 3700.3
    },
    "ETHPLN": 13198.12,
    "ETHUSD": 3615.85
  },
  {
    "timestamp": "2025-07-18 11:25:32",
    "WETH": 0.00011131,
    "USDC": 0.25504049,
    "pool": {
      "krs_usdc": 975.3798794595659,
      "usdc": 764.82083,
      "krs_weth": 1593.1616019980136,
      "weth": 0.002060830787274543,
      "value_usd": 1013.76,
      "value_eth": 0.281222,
      "value_pln": 3698.29
    },
    "ETHPLN": 13150.79,
    "ETHUSD": 3604.84
  },
  {
    "timestamp": "2025-07-18 11:41:37",
    "WETH": 0.00011131,
    "USDC": 0.25504049,
    "pool": {
      "krs_usdc": 975.3798794595659,
      "usdc": 764.82083,
      "krs_weth": 1593.1616019980136,
      "weth": 0.002060830787274543,
      "value_usd": 1013.76,
      "value_eth": 0.28104,
      "value_pln": 3698.02
    },
    "ETHPLN": 13158.33,
    "ETHUSD": 3607.17
  },
  {
    "timestamp": "2025-07-18 11:55:53",
    "WETH": 0.00011131,
    "USDC": 0.25504049,
    "pool": {
      "krs_usdc": 975.3798794595659,
      "usdc": 764.82083,
      "krs_weth": 1593.1616019980136,
      "weth": 0.002060830787274543,
      "value_usd": 1013.76,
      "value_eth": 0.280338,
      "value_pln": 3698.58
    },
    "ETHPLN": 13193.26,
    "ETHUSD": 3616.2
  },
  {
    "timestamp": "2025-07-18 12:48:30",
    "WETH": 0.00011131,
    "USDC": 0.25504049,
    "pool": {
      "krs_usdc": 975.3798794595659,
      "usdc": 764.82083,
      "krs_weth": 1593.1616019980136,
      "weth": 0.002060830787274543,
      "value_usd": 1013.76,
      "value_eth": 0.280733,
      "value_pln": 3697.92
    },
    "ETHPLN": 13172.34,
    "ETHUSD": 3611.11
  },
  {
    "timestamp": "2025-07-18 13:28:20",
    "WETH": 0.00011131,
    "USDC": 0.25504049,
    "pool": {
      "krs_usdc": 975.3798794595659,
      "usdc": 764.82083,
      "krs_weth": 1593.1616019980136,
      "weth": 0.002060830787274543,
      "value_usd": 1013.76,
      "value_eth": 0.279621,
      "value_pln": 3692.76
    },
    "ETHPLN": 13206.31,
    "ETHUSD": 3625.48
  },
  {
    "timestamp": "2025-07-18 13:55:56",
    "WETH": 0.00011131,
    "USDC": 0.25504049,
    "pool": {
      "krs_usdc": 975.3798794595659,
      "usdc": 764.82083,
      "krs_weth": 1593.1616019980136,
      "weth": 0.002060830787274543,
      "value_usd": 1013.76,
      "value_eth": 0.277862,
      "value_pln": 3694.62
    },
    "ETHPLN": 13296.6,
    "ETHUSD": 3648.43
  },
  {
    "timestamp": "2025-07-18 14:21:53",
    "WETH": 0.00011131,
    "USDC": 0.25504049,
    "pool": {
      "krs_usdc": 975.3798794595659,
      "usdc": 764.82083,
      "krs_weth": 1593.1616019980136,
      "weth": 0.002060830787274543,
      "value_usd": 1013.76,
      "value_eth": 0.27796,
      "value_pln": 3696.37
    },
    "ETHPLN": 13298.19,
    "ETHUSD": 3647.14
  },
  {
    "timestamp": "2025-07-18 14:47:47",
    "WETH": 0.00011131,
    "USDC": 0.25504049,
    "pool": {
      "krs_usdc": 975.3798794595659,
      "usdc": 764.82083,
      "krs_weth": 1593.1616019980136,
      "weth": 0.002060830787274543,
      "value_usd": 1013.76,
      "value_eth": 0.283073,
      "value_pln": 3690.96
    },
    "ETHPLN": 13038.88,
    "ETHUSD": 3581.26
  },
  {
    "timestamp": "2025-07-18 14:58:48",
    "WETH": 0.00011131,
    "USDC": 0.25504049,
    "pool": {
      "krs_usdc": 975.3798794595659,
      "usdc": 764.82083,
      "krs_weth": 1593.1616019980136,
      "weth": 0.002060830787274543,
      "value_usd": 1013.76,
      "value_eth": 0.282698,
      "value_pln": 3700.49
    },
    "ETHPLN": 13089.89,
    "ETHUSD": 3586.01
  },
  {
    "timestamp": "2025-07-18 15:30:06",
    "WETH": 0.00011131,
    "USDC": 0.25504049,
    "pool": {
      "krs_usdc": 975.3798794595659,
      "usdc": 764.82083,
      "krs_weth": 1593.1616019980136,
      "weth": 0.002060830787274543,
      "value_usd": 1013.76,
      "value_eth": 0.286306,
      "value_pln": 3696.32
    },
    "ETHPLN": 12910.39,
    "ETHUSD": 3540.83
  },
  {
    "timestamp": "2025-07-18 15:49:43",
    "WETH": 0.00011131,
    "USDC": 0.25504049,
    "pool": {
      "krs_usdc": 975.3798794595659,
      "usdc": 764.82083,
      "krs_weth": 1593.1616019980136,
      "weth": 0.002060830787274543,
      "value_usd": 1013.76,
      "value_eth": 0.285818,
      "value_pln": 3696.3
    },
    "ETHPLN": 12932.35,
    "ETHUSD": 3546.87
  },
  {
    "timestamp": "2025-07-18 16:11:56",
    "WETH": 0.00011131,
    "USDC": 0.25504049,
    "pool": {
      "krs_usdc": 975.3798794595659,
      "usdc": 764.82083,
      "krs_weth": 1593.1616019980136,
      "weth": 0.002060830787274543,
      "value_usd": 1013.76,
      "value_eth": 0.284266,
      "value_pln": 3697.14
    },
    "ETHPLN": 13005.88,
    "ETHUSD": 3566.23
  },
  {
    "timestamp": "2025-07-18 16:46:31",
    "WETH": 0.00011131,
    "USDC": 0.25504049,
    "pool": {
      "krs_usdc": 975.3798794595659,
      "usdc": 764.82083,
      "krs_weth": 1593.1616019980136,
      "weth": 0.002060830787274543,
      "value_usd": 1013.76,
      "value_eth": 0.283471,
      "value_pln": 3699.66
    },
    "ETHPLN": 13051.28,
    "ETHUSD": 3576.24
  },
  {
    "timestamp": "2025-07-18 17:09:57",
    "WETH": 0.00011131,
    "USDC": 0.25504049,
    "pool": {
      "krs_usdc": 975.3798794595659,
      "usdc": 764.82083,
      "krs_weth": 1593.1616019980136,
      "weth": 0.002060830787274543,
      "value_usd": 1013.76,
      "value_eth": 0.283296,
      "value_pln": 3701.03
    },
    "ETHPLN": 13064.16,
    "ETHUSD": 3578.44
  },
  {
    "timestamp": "2025-07-18 17:35:45",
    "WETH": 0.00011131,
    "USDC": 0.25504049,
    "pool": {
      "krs_usdc": 975.3798794595659,
      "usdc": 764.82083,
      "krs_weth": 1593.1616019980136,
      "weth": 0.002060830787274543,
      "value_usd": 1013.76,
      "value_eth": 0.281011,
      "value_pln": 3700.67
    },
    "ETHPLN": 13169.16,
    "ETHUSD": 3607.55
  },
  {
    "timestamp": "2025-07-18 17:52:59",
    "WETH": 0.00011131,
    "USDC": 0.25504049,
    "pool": {
      "krs_usdc": 975.3798794595659,
      "usdc": 764.82083,
      "krs_weth": 1593.1616019980136,
      "weth": 0.002060830787274543,
      "value_usd": 1013.76,
      "value_eth": 0.281674,
      "value_pln": 3701.41
    },
    "ETHPLN": 13140.75,
    "ETHUSD": 3599.05
  },
  {
    "timestamp": "2025-07-18 18:29:35",
    "WETH": 0.00011131,
    "USDC": 0.25504049,
    "pool": {
      "krs_usdc": 975.3798794595659,
      "usdc": 764.82083,
      "krs_weth": 1593.1616019980136,
      "weth": 0.002060830787274543,
      "value_usd": 1013.76,
      "value_eth": 0.282153,
      "value_pln": 3706.5
    },
    "ETHPLN": 13136.47,
    "ETHUSD": 3592.94
  },
  {
    "timestamp": "2025-07-18 18:54:42",
    "WETH": 0.00011131,
    "USDC": 0.25504049,
    "pool": {
      "krs_usdc": 975.3798794595659,
      "usdc": 764.82083,
      "krs_weth": 1593.1616019980136,
      "weth": 0.002060830787274543,
      "value_usd": 1013.76,
      "value_eth": 0.282422,
      "value_pln": 3701.12
    },
    "ETHPLN": 13104.94,
    "ETHUSD": 3589.52
  },
  {
    "timestamp": "2025-07-18 19:17:07",
    "WETH": 0.00011131,
    "USDC": 0.25504049,
    "pool": {
      "krs_usdc": 975.3798794595659,
      "usdc": 764.82083,
      "krs_weth": 1593.1616019980136,
      "weth": 0.002060830787274543,
      "value_usd": 1013.76,
      "value_eth": 0.285439,
      "value_pln": 3704.15
    },
    "ETHPLN": 12977.02,
    "ETHUSD": 3551.58
  },
  {
    "timestamp": "2025-07-18 19:31:23",
    "WETH": 0.00011131,
    "USDC": 0.25504049,
    "pool": {
      "krs_usdc": 975.3798794595659,
      "usdc": 764.82083,
      "krs_weth": 1593.1616019980136,
      "weth": 0.002060830787274543,
      "value_usd": 1013.76,
      "value_eth": 0.283305,
      "value_pln": 3703.42
    },
    "ETHPLN": 13072.19,
    "ETHUSD": 3578.33
  },
  {
    "timestamp": "2025-07-18 19:46:44",
    "WETH": 0.00011131,
    "USDC": 0.25504049,
    "pool": {
      "krs_usdc": 975.3798794595659,
      "usdc": 764.82083,
      "krs_weth": 1593.1616019980136,
      "weth": 0.002060830787274543,
      "value_usd": 1013.76,
      "value_eth": 0.283872,
      "value_pln": 3703.44
    },
    "ETHPLN": 13046.18,
    "ETHUSD": 3571.19
  },
  {
    "timestamp": "2025-07-18 19:57:01",
    "WETH": 0.00011131,
    "USDC": 0.25504049,
    "pool": {
      "krs_usdc": 975.3798794595659,
      "usdc": 764.82083,
      "krs_weth": 1593.1616019980136,
      "weth": 0.002060830787274543,
      "value_usd": 1013.76,
      "value_eth": 0.285075,
      "value_pln": 3704.91
    },
    "ETHPLN": 12996.26,
    "ETHUSD": 3556.11
  },
  {
    "timestamp": "2025-07-18 20:27:29",
    "WETH": 0.00011131,
    "USDC": 0.25504049,
    "pool": {
      "krs_usdc": 975.3798794595659,
      "usdc": 764.82083,
      "krs_weth": 1593.1616019980136,
      "weth": 0.002060830787274543,
      "value_usd": 1013.76,
      "value_eth": 0.287702,
      "value_pln": 3699.61
    },
    "ETHPLN": 12859.2,
    "ETHUSD": 3523.65
  },
  {
    "timestamp": "2025-07-18 20:45:40",
    "WETH": 0.00011131,
    "USDC": 0.25504049,
    "pool": {
      "krs_usdc": 975.3798794595659,
      "usdc": 764.82083,
      "krs_weth": 1593.1616019980136,
      "weth": 0.002060830787274543,
      "value_usd": 1013.76,
      "value_eth": 0.290173,
      "value_pln": 3703.33
    },
    "ETHPLN": 12762.48,
    "ETHUSD": 3493.64
  },
  {
    "timestamp": "2025-07-18 20:56:49",
    "WETH": 0.00011131,
    "USDC": 0.25504049,
    "pool": {
      "krs_usdc": 975.3798794595659,
      "usdc": 764.82083,
      "krs_weth": 1593.1616019980136,
      "weth": 0.002060830787274543,
      "value_usd": 1013.76,
      "value_eth": 0.288714,
      "value_pln": 3703.09
    },
    "ETHPLN": 12826.15,
    "ETHUSD": 3511.29
  },
  {
    "timestamp": "2025-07-18 21:23:33",
    "WETH": 0.00011131,
    "USDC": 0.25504049,
    "pool": {
      "krs_usdc": 975.3798794595659,
      "usdc": 764.82083,
      "krs_weth": 1593.1616019980136,
      "weth": 0.002060830787274543,
      "value_usd": 1013.76,
      "value_eth": 0.285484,
      "value_pln": 3702.43
    },
    "ETHPLN": 12968.95,
    "ETHUSD": 3551.02
  },
  {
    "timestamp": "2025-07-18 21:41:25",
    "WETH": 0.00011131,
    "USDC": 0.25504049,
    "pool": {
      "krs_usdc": 975.3798794595659,
      "usdc": 764.82083,
      "krs_weth": 1593.1616019980136,
      "weth": 0.002060830787274543,
      "value_usd": 1013.76,
      "value_eth": 0.284973,
      "value_pln": 3702.07
    },
    "ETHPLN": 12990.95,
    "ETHUSD": 3557.39
  },
  {
    "timestamp": "2025-07-18 21:55:30",
    "WETH": 0.00011131,
    "USDC": 0.25504049,
    "pool": {
      "krs_usdc": 975.3798794595659,
      "usdc": 764.82083,
      "krs_weth": 1593.1616019980136,
      "weth": 0.002060830787274543,
      "value_usd": 1013.76,
      "value_eth": 0.284539,
      "value_pln": 3702.25
    },
    "ETHPLN": 13011.43,
    "ETHUSD": 3562.82
  },
  {
    "timestamp": "2025-07-18 22:20:45",
    "WETH": 0.00011131,
    "USDC": 0.25504049,
    "pool": {
      "krs_usdc": 975.3798794595659,
      "usdc": 764.82083,
      "krs_weth": 1593.1616019980136,
      "weth": 0.002060830787274543,
      "value_usd": 1013.76,
      "value_eth": 0.286115,
      "value_pln": 3702.53
    },
    "ETHPLN": 12940.7,
    "ETHUSD": 3543.19
  },
  {
    "timestamp": "2025-07-18 22:45:24",
    "WETH": 0.00011131,
    "USDC": 0.25504049,
    "pool": {
      "krs_usdc": 975.3798794595659,
      "usdc": 764.82083,
      "krs_weth": 1593.1616019980136,
      "weth": 0.002060830787274543,
      "value_usd": 1013.76,
      "value_eth": 0.284174,
      "value_pln": 3702.43
    },
    "ETHPLN": 13028.74,
    "ETHUSD": 3567.39
  },
  {
    "timestamp": "2025-07-18 22:56:46",
    "WETH": 0.00011131,
    "USDC": 0.25504049,
    "pool": {
      "krs_usdc": 975.3798794595659,
      "usdc": 764.82083,
      "krs_weth": 1593.1616019980136,
      "weth": 0.002060830787274543,
      "value_usd": 1013.76,
      "value_eth": 0.285844,
      "value_pln": 3701.66
    },
    "ETHPLN": 12949.95,
    "ETHUSD": 3546.55
  },
  {
    "timestamp": "2025-07-18 23:23:12",
    "WETH": 0.00011131,
    "USDC": 0.25504049,
    "pool": {
      "krs_usdc": 975.3798794595659,
      "usdc": 764.82083,
      "krs_weth": 1593.1616019980136,
      "weth": 0.002060830787274543,
      "value_usd": 1013.76,
      "value_eth": 0.286646,
      "value_pln": 3702.43
    },
    "ETHPLN": 12916.4,
    "ETHUSD": 3536.63
  },
  {
    "timestamp": "2025-07-18 23:41:36",
    "WETH": 0.00011131,
    "USDC": 0.25504049,
    "pool": {
      "krs_usdc": 975.3798794595659,
      "usdc": 764.82083,
      "krs_weth": 1593.1616019980136,
      "weth": 0.002060830787274543,
      "value_usd": 1013.76,
      "value_eth": 0.286489,
      "value_pln": 3702.77
    },
    "ETHPLN": 12924.65,
    "ETHUSD": 3538.56
  },
  {
    "timestamp": "2025-07-18 23:55:46",
    "WETH": 0.00011131,
    "USDC": 0.25504049,
    "pool": {
      "krs_usdc": 975.3798794595659,
      "usdc": 764.82083,
      "krs_weth": 1593.1616019980136,
      "weth": 0.002060830787274543,
      "value_usd": 1013.76,
      "value_eth": 0.285812,
      "value_pln": 3702.82
    },
    "ETHPLN": 12955.42,
    "ETHUSD": 3546.94
  },
  {
    "timestamp": "2025-07-19 01:48:19",
    "WETH": 0.00011131,
    "USDC": 0.25504049,
    "pool": {
      "krs_usdc": 975.3798794595659,
      "usdc": 764.82083,
      "krs_weth": 1593.1616019980136,
      "weth": 0.002060830787274543,
      "value_usd": 1013.76,
      "value_eth": 0.286029,
      "value_pln": 3702.43
    },
    "ETHPLN": 12944.23,
    "ETHUSD": 3544.25
  },
  {
    "timestamp": "2025-07-19 03:15:49",
    "WETH": 0.00011131,
    "USDC": 0.25504049,
    "pool": {
      "krs_usdc": 975.3798794595659,
      "usdc": 764.82083,
      "krs_weth": 1593.1616019980136,
      "weth": 0.002060830787274543,
      "value_usd": 1013.76,
      "value_eth": 0.283209,
      "value_pln": 3702.42
    },
    "ETHPLN": 13073.13,
    "ETHUSD": 3579.55
  },
  {
    "timestamp": "2025-07-19 04:02:52",
    "WETH": 0.00011131,
    "USDC": 0.25504049,
    "pool": {
      "krs_usdc": 975.3798794595659,
      "usdc": 764.82083,
      "krs_weth": 1593.1616019980136,
      "weth": 0.002060830787274543,
      "value_usd": 1013.76,
      "value_eth": 0.282298,
      "value_pln": 3703.63
    },
    "ETHPLN": 13119.6,
    "ETHUSD": 3591.1
  },
  {
    "timestamp": "2025-07-19 04:41:56",
    "WETH": 0.00011131,
    "USDC": 0.25504049,
    "pool": {
      "krs_usdc": 975.3798794595659,
      "usdc": 764.82083,
      "krs_weth": 1593.1616019980136,
      "weth": 0.002060830787274543,
      "value_usd": 1013.76,
      "value_eth": 0.282082,
      "value_pln": 3702.05
    },
    "ETHPLN": 13124.04,
    "ETHUSD": 3593.85
  },
  {
    "timestamp": "2025-07-19 05:02:06",
    "WETH": 0.00011131,
    "USDC": 0.25504049,
    "pool": {
      "krs_usdc": 975.3798794595659,
      "usdc": 764.82083,
      "krs_weth": 1593.1616019980136,
      "weth": 0.002060830787274543,
      "value_usd": 1013.76,
      "value_eth": 0.282333,
      "value_pln": 3703.0
    },
    "ETHPLN": 13115.7,
    "ETHUSD": 3590.65
  },
  {
    "timestamp": "2025-07-19 05:34:46",
    "WETH": 0.00011131,
    "USDC": 0.25504049,
    "pool": {
      "krs_usdc": 975.3798794595659,
      "usdc": 764.82083,
      "krs_weth": 1593.1616019980136,
      "weth": 0.002060830787274543,
      "value_usd": 1013.76,
      "value_eth": 0.282739,
      "value_pln": 3702.98
    },
    "ETHPLN": 13096.83,
    "ETHUSD": 3585.5
  },
  {
    "timestamp": "2025-07-19 05:50:21",
    "WETH": 0.00011131,
    "USDC": 0.25504049,
    "pool": {
      "krs_usdc": 975.3798794595659,
      "usdc": 764.82083,
      "krs_weth": 1593.1616019980136,
      "weth": 0.002060830787274543,
      "value_usd": 1013.76,
      "value_eth": 0.282317,
      "value_pln": 3702.43
    },
    "ETHPLN": 13114.46,
    "ETHUSD": 3590.86
  },
  {
    "timestamp": "2025-07-19 06:11:57",
    "WETH": 0.00011131,
    "USDC": 0.25504049,
    "pool": {
      "krs_usdc": 975.3798794595659,
      "usdc": 764.82083,
      "krs_weth": 1593.1616019980136,
      "weth": 0.002060830787274543,
      "value_usd": 1013.76,
      "value_eth": 0.282662,
      "value_pln": 3702.42
    },
    "ETHPLN": 13098.39,
    "ETHUSD": 3586.47
  },
  {
    "timestamp": "2025-07-19 06:46:35",
    "WETH": 0.00011131,
    "USDC": 0.25504049,
    "pool": {
      "krs_usdc": 975.3798794595659,
      "usdc": 764.82083,
      "krs_weth": 1593.1616019980136,
      "weth": 0.002060830787274543,
      "value_usd": 1013.76,
      "value_eth": 0.2835,
      "value_pln": 3702.43
    },
    "ETHPLN": 13059.7,
    "ETHUSD": 3575.87
  },
  {
    "timestamp": "2025-07-19 06:59:50",
    "WETH": 0.00011131,
    "USDC": 0.25504049,
    "pool": {
      "krs_usdc": 975.3798794595659,
      "usdc": 764.82083,
      "krs_weth": 1593.1616019980136,
      "weth": 0.002060830787274543,
      "value_usd": 1013.76,
      "value_eth": 0.283474,
      "value_pln": 3701.83
    },
    "ETHPLN": 13058.81,
    "ETHUSD": 3576.2
  },
  {
    "timestamp": "2025-07-19 07:26:13",
    "WETH": 0.00011131,
    "USDC": 0.25504049,
    "pool": {
      "krs_usdc": 975.3798794595659,
      "usdc": 764.82083,
      "krs_weth": 1593.1616019980136,
      "weth": 0.002060830787274543,
      "value_usd": 1013.76,
      "value_eth": 0.282931,
      "value_pln": 3703.53
    },
    "ETHPLN": 13089.85,
    "ETHUSD": 3583.06
  },
  {
    "timestamp": "2025-07-19 07:40:37",
    "WETH": 0.00011131,
    "USDC": 0.25504049,
    "pool": {
      "krs_usdc": 975.3798794595659,
      "usdc": 764.82083,
      "krs_weth": 1593.1616019980136,
      "weth": 0.002060830787274543,
      "value_usd": 1013.76,
      "value_eth": 0.283418,
      "value_pln": 3702.31
    },
    "ETHPLN": 13063.1,
    "ETHUSD": 3576.91
  },
  {
    "timestamp": "2025-07-19 07:55:32",
    "WETH": 0.00011131,
    "USDC": 0.25504049,
    "pool": {
      "krs_usdc": 975.3798794595659,
      "usdc": 764.82083,
      "krs_weth": 1593.1616019980136,
      "weth": 0.002060830787274543,
      "value_usd": 1013.76,
      "value_eth": 0.283505,
      "value_pln": 3702.43
    },
    "ETHPLN": 13059.5,
    "ETHUSD": 3575.81
  },
  {
    "timestamp": "2025-07-19 08:26:31",
    "WETH": 0.00011131,
    "USDC": 0.25504049,
    "pool": {
      "krs_usdc": 975.3798794595659,
      "usdc": 764.82083,
      "krs_weth": 1593.1616019980136,
      "weth": 0.002060830787274543,
      "value_usd": 1013.76,
      "value_eth": 0.284686,
      "value_pln": 3702.25
    },
    "ETHPLN": 13004.65,
    "ETHUSD": 3560.97
  },
  {
    "timestamp": "2025-07-19 08:49:13",
    "WETH": 0.00011131,
    "USDC": 0.25504049,
    "pool": {
      "krs_usdc": 975.3798794595659,
      "usdc": 764.82083,
      "krs_weth": 1593.1616019980136,
      "weth": 0.002060830787274543,
      "value_usd": 1013.76,
      "value_eth": 0.285103,
      "value_pln": 3702.71
    },
    "ETHPLN": 12987.29,
    "ETHUSD": 3555.77
  },
  {
    "timestamp": "2025-07-19 08:59:51",
    "WETH": 0.00011131,
    "USDC": 0.25504049,
    "pool": {
      "krs_usdc": 975.3798794595659,
      "usdc": 764.82083,
      "krs_weth": 1593.1616019980136,
      "weth": 0.002060830787274543,
      "value_usd": 1013.76,
      "value_eth": 0.284992,
      "value_pln": 3702.36
    },
    "ETHPLN": 12991.09,
    "ETHUSD": 3557.15
  },
  {
    "timestamp": "2025-07-19 09:28:33",
    "WETH": 0.00011131,
    "USDC": 0.25504049,
    "pool": {
      "krs_usdc": 975.3798794595659,
      "usdc": 764.82083,
      "krs_weth": 1593.1616019980136,
      "weth": 0.002060830787274543,
      "value_usd": 1013.76,
      "value_eth": 0.284878,
      "value_pln": 3702.6
    },
    "ETHPLN": 12997.15,
    "ETHUSD": 3558.58
  },
  {
    "timestamp": "2025-07-19 09:44:02",
    "WETH": 0.00011131,
    "USDC": 0.25504049,
    "pool": {
      "krs_usdc": 975.3798794595659,
      "usdc": 764.82083,
      "krs_weth": 1593.1616019980136,
      "weth": 0.002060830787274543,
      "value_usd": 1013.76,
      "value_eth": 0.284491,
      "value_pln": 3702.54
    },
    "ETHPLN": 13014.64,
    "ETHUSD": 3563.42
  },
  {
    "timestamp": "2025-07-19 09:55:37",
    "WETH": 0.00011131,
    "USDC": 0.25504049,
    "pool": {
      "krs_usdc": 975.3798794595659,
      "usdc": 764.82083,
      "krs_weth": 1593.1616019980136,
      "weth": 0.002060830787274543,
      "value_usd": 1013.76,
      "value_eth": 0.284539,
      "value_pln": 3702.35
    },
    "ETHPLN": 13011.78,
    "ETHUSD": 3562.82
  },
  {
    "timestamp": "2025-07-19 10:22:17",
    "WETH": 0.00011131,
    "USDC": 0.25504049,
    "pool": {
      "krs_usdc": 975.3798794595659,
      "usdc": 764.82083,
      "krs_weth": 1593.1616019980136,
      "weth": 0.002060830787274543,
      "value_usd": 1013.76,
      "value_eth": 0.28515,
      "value_pln": 3703.18
    },
    "ETHPLN": 12986.79,
    "ETHUSD": 3555.18
  },
  {
    "timestamp": "2025-07-19 10:46:14",
    "WETH": 0.00011131,
    "USDC": 0.25504049,
    "pool": {
      "krs_usdc": 975.3798794595659,
      "usdc": 764.82083,
      "krs_weth": 1593.1616019980136,
      "weth": 0.002060830787274543,
      "value_usd": 1013.76,
      "value_eth": 0.284377,
      "value_pln": 3702.42
    },
    "ETHPLN": 13019.41,
    "ETHUSD": 3564.84
  },
  {
    "timestamp": "2025-07-19 10:56:25",
    "WETH": 0.00011131,
    "USDC": 0.25504049,
    "pool": {
      "krs_usdc": 975.3798794595659,
      "usdc": 764.82083,
      "krs_weth": 1593.1616019980136,
      "weth": 0.002060830787274543,
      "value_usd": 1013.76,
      "value_eth": 0.284534,
      "value_pln": 3702.02
    },
    "ETHPLN": 13010.83,
    "ETHUSD": 3562.88
  },
  {
    "timestamp": "2025-07-19 11:18:54",
    "WETH": 0.00011131,
    "USDC": 0.25504049,
    "pool": {
      "krs_usdc": 975.3798794595659,
      "usdc": 764.82083,
      "krs_weth": 1593.1616019980136,
      "weth": 0.002060830787274543,
      "value_usd": 1013.76,
      "value_eth": 0.285156,
      "value_pln": 3702.43
    },
    "ETHPLN": 12983.84,
    "ETHUSD": 3555.1
  },
  {
    "timestamp": "2025-07-19 11:32:43",
    "WETH": 0.00011131,
    "USDC": 0.25504049,
    "pool": {
      "krs_usdc": 975.3798794595659,
      "usdc": 764.82083,
      "krs_weth": 1593.1616019980136,
      "weth": 0.002060830787274543,
      "value_usd": 1013.76,
      "value_eth": 0.284242,
      "value_pln": 3702.42
    },
    "ETHPLN": 13025.62,
    "ETHUSD": 3566.54
  },
  {
    "timestamp": "2025-07-19 11:45:55",
    "WETH": 0.00011131,
    "USDC": 0.25504049,
    "pool": {
      "krs_usdc": 975.3798794595659,
      "usdc": 764.82083,
      "krs_weth": 1593.1616019980136,
      "weth": 0.002060830787274543,
      "value_usd": 1013.76,
      "value_eth": 0.284205,
      "value_pln": 3701.67
    },
    "ETHPLN": 13024.63,
    "ETHUSD": 3567.0
  },
  {
    "timestamp": "2025-07-19 11:56:35",
    "WETH": 0.00011131,
    "USDC": 0.25504049,
    "pool": {
      "krs_usdc": 975.3798794595659,
      "usdc": 764.82083,
      "krs_weth": 1593.1616019980136,
      "weth": 0.002060830787274543,
      "value_usd": 1013.76,
      "value_eth": 0.285095,
      "value_pln": 3701.5
    },
    "ETHPLN": 12983.38,
    "ETHUSD": 3555.86
  },
  {
    "timestamp": "2025-07-19 12:45:42",
    "WETH": 0.00011131,
    "USDC": 0.25504049,
    "pool": {
      "krs_usdc": 975.3798794595659,
      "usdc": 764.82083,
      "krs_weth": 1593.1616019980136,
      "weth": 0.002060830787274543,
      "value_usd": 1013.76,
      "value_eth": 0.285342,
      "value_pln": 3702.43
    },
    "ETHPLN": 12975.41,
    "ETHUSD": 3552.79
  },
  {
    "timestamp": "2025-07-19 13:20:15",
    "WETH": 0.00011131,
    "USDC": 0.25504049,
    "pool": {
      "krs_usdc": 975.3798794595659,
      "usdc": 764.82083,
      "krs_weth": 1593.1616019980136,
      "weth": 0.002060830787274543,
      "value_usd": 1013.76,
      "value_eth": 0.284573,
      "value_pln": 3702.43
    },
    "ETHPLN": 13010.47,
    "ETHUSD": 3562.39
  },
  {
    "timestamp": "2025-07-19 13:44:53",
    "WETH": 0.00011131,
    "USDC": 0.25504049,
    "pool": {
      "krs_usdc": 975.3798794595659,
      "usdc": 764.82083,
      "krs_weth": 1593.1616019980136,
      "weth": 0.002060830787274543,
      "value_usd": 1013.76,
      "value_eth": 0.284163,
      "value_pln": 3702.15
    },
    "ETHPLN": 13028.28,
    "ETHUSD": 3567.53
  },
  {
    "timestamp": "2025-07-19 13:56:53",
    "WETH": 0.00011131,
    "USDC": 0.25504049,
    "pool": {
      "krs_usdc": 975.3798794595659,
      "usdc": 764.82083,
      "krs_weth": 1593.1616019980136,
      "weth": 0.002060830787274543,
      "value_usd": 1013.76,
      "value_eth": 0.284651,
      "value_pln": 3702.2
    },
    "ETHPLN": 13006.09,
    "ETHUSD": 3561.41
  },
  {
    "timestamp": "2025-07-19 14:21:37",
    "WETH": 0.00011131,
    "USDC": 0.25504049,
    "pool": {
      "krs_usdc": 975.3798794595659,
      "usdc": 764.82083,
      "krs_weth": 1593.1616019980136,
      "weth": 0.002060830787274543,
      "value_usd": 1013.76,
      "value_eth": 0.285312,
      "value_pln": 3702.44
    },
    "ETHPLN": 12976.79,
    "ETHUSD": 3553.16
  },
  {
    "timestamp": "2025-07-19 14:42:50",
    "WETH": 0.00011131,
    "USDC": 0.25504049,
    "pool": {
      "krs_usdc": 975.3798794595659,
      "usdc": 764.82083,
      "krs_weth": 1593.1616019980136,
      "weth": 0.002060830787274543,
      "value_usd": 1013.76,
      "value_eth": 0.285845,
      "value_pln": 3702.58
    },
    "ETHPLN": 12953.11,
    "ETHUSD": 3546.54
  },
  {
    "timestamp": "2025-07-19 14:55:41",
    "WETH": 0.00011131,
    "USDC": 0.25504049,
    "pool": {
      "krs_usdc": 975.3798794595659,
      "usdc": 764.82083,
      "krs_weth": 1593.1616019980136,
      "weth": 0.002060830787274543,
      "value_usd": 1013.76,
      "value_eth": 0.285904,
      "value_pln": 3701.5
    },
    "ETHPLN": 12946.63,
    "ETHUSD": 3545.8
  },
  {
    "timestamp": "2025-07-19 15:20:40",
    "WETH": 0.00011131,
    "USDC": 0.25504049,
    "pool": {
      "krs_usdc": 975.3798794595659,
      "usdc": 764.82083,
      "krs_weth": 1593.1616019980136,
      "weth": 0.002060830787274543,
      "value_usd": 1013.76,
      "value_eth": 0.285753,
      "value_pln": 3702.43
    },
    "ETHPLN": 12956.76,
    "ETHUSD": 3547.68
  },
  {
    "timestamp": "2025-07-19 15:41:47",
    "WETH": 0.00011131,
    "USDC": 0.25504049,
    "pool": {
      "krs_usdc": 975.3798794595659,
      "usdc": 764.82083,
      "krs_weth": 1593.1616019980136,
      "weth": 0.002060830787274543,
      "value_usd": 1013.76,
      "value_eth": 0.285213,
      "value_pln": 3702.42
    },
    "ETHPLN": 12981.24,
    "ETHUSD": 3554.39
  },
  {
    "timestamp": "2025-07-19 15:56:58",
    "WETH": 0.00011131,
    "USDC": 0.25504049,
    "pool": {
      "krs_usdc": 975.3798794595659,
      "usdc": 764.82083,
      "krs_weth": 1593.1616019980136,
      "weth": 0.002060830787274543,
      "value_usd": 1013.76,
      "value_eth": 0.285054,
      "value_pln": 3702.65
    },
    "ETHPLN": 12989.32,
    "ETHUSD": 3556.38
  },
  {
    "timestamp": "2025-07-19 16:29:16",
    "WETH": 0.00011131,
    "USDC": 0.25504049,
    "pool": {
      "krs_usdc": 975.3798794595659,
      "usdc": 764.82083,
      "krs_weth": 1593.1616019980136,
      "weth": 0.002060830787274543,
      "value_usd": 1013.76,
      "value_eth": 0.285804,
      "value_pln": 3703.69
    },
    "ETHPLN": 12958.84,
    "ETHUSD": 3547.04
  },
  {
    "timestamp": "2025-07-19 16:51:10",
    "WETH": 0.00011131,
    "USDC": 0.25504049,
    "pool": {
      "krs_usdc": 975.3798794595659,
      "usdc": 764.82083,
      "krs_weth": 1593.1616019980136,
      "weth": 0.002060830787274543,
      "value_usd": 1013.76,
      "value_eth": 0.284187,
      "value_pln": 3702.18
    },
    "ETHPLN": 13027.28,
    "ETHUSD": 3567.23
  }
]